[
    {
        "_id": "7818534649918",
        "id": "7818534649918",
        "title": "5Pcs Tactical 3.5\" Plastic Carabiner Molle Clip ITW Keychain D-Shape Hard Spring Snap Gear Hook Outdoor Camping Hiking EDC Tools",
        "description": "<h1>SPECIFICATIONS</h1><p><span>Brand Name</span>: <span style=\"color:#333\">NoEnName_Null</span></p><p><span>Choice</span>: <span style=\"color:#333\">yes</span></p><p><span>Color</span>: <span style=\"color:#333\">Black/Army Green/Khaki</span></p><p><span>Electric</span>: <span style=\"color:#333\">No</span></p><p><span>Hign-concerned Chemical</span>: <span style=\"color:#333\">None</span></p><p><span>Lock Type</span>: <span style=\"color:#333\">Wire Lock</span></p><p><span>Material</span>: <span style=\"color:#333\">Plastic</span></p><p><span>Origin</span>: <span style=\"color:#333\">Mainland China</span></p><p><span>Shape</span>: <span style=\"color:#333\">D-Shape</span></p><p><span>Type</span>: <span style=\"color:#333\">Pocket, Multi Tools</span></p><p><span>semi_Choice</span>: <span style=\"color:#333\">yes</span></p><div class=\"detailmodule_html\"><div class=\"detail-desc-decorate-richtext\">\n<p style=\"font-size:16px;font-weight:bold;text-align:left;color:rgb(67, 70, 73)\" align=\"left\">Feature:</p>\n<p style=\"font-size:13px;text-align:left;color:rgb(67, 70, 73)\" align=\"left\">Made of high-quality ABS plastic - toughness and resistance to wear and tear, withstand a wide range of temperatures<br>Ribbed surface - improves grip, so it won't slip out of your hands<br>Palm sized design - easy one hand operation to lock or open<br>Spring-loaded gate - makes it easy to clip and unclip items<br>Wide applications - great accessory for daily life<br>Unloading heavy bags - lightweight, one of the best outdoor partners<br>Dimensions: 3.3\"\" x 2.4\"\" (8.5 x 6 cm)</p>\n<div>\n<img style=\"width:100%;height:auto\" width=\"100%\" height=\"auto\" src=\"https://ae01.alicdn.com/kf/S3fddb1bc556647f4b9daeefdfb0de0e7Y.jpg?width=679&amp;height=673&amp;hash=1352\" slate-data-type=\"image\"><img style=\"width:100%;height:auto\" width=\"100%\" height=\"auto\" src=\"https://ae01.alicdn.com/kf/S374c149ecac441a1b1f1692f412ce6c05.jpg?width=1001&amp;height=1341&amp;hash=2342\" slate-data-type=\"image\">\n</div>\n</div></div><p><br></p>",
        "vendor": "My Store",
        "productType": "",
        "handle": "5pcs-tactical-3-5-plastic-carabiner-molle-clip-itw-keychain-d-shape-hard-spring-snap-gear-hook-outdoor-camping-hiking-edc-tools",
        "status": "ACTIVE",
        "tags": [],
        "images": [
            {
                "url": "https://cdn.shopify.com/s/files/1/0627/6022/2782/files/S9f2deb4152124a5f9760cdb33d7ca5c7D.webp?v=1752125921",
                "altText": null
            },
            {
                "url": "https://cdn.shopify.com/s/files/1/0627/6022/2782/files/See53b9586f1e4acdb87db7300dd1cde9m.webp?v=1752125917",
                "altText": null
            },
            {
                "url": "https://cdn.shopify.com/s/files/1/0627/6022/2782/files/S99f3c6e1ed154976a3006720c09a92c9g.webp?v=1752125916",
                "altText": null
            },
            {
                "url": "https://cdn.shopify.com/s/files/1/0627/6022/2782/files/S6a4d9de59f8b4fb090c5dbd6aa1e5f46o.webp?v=1752125917",
                "altText": null
            },
            {
                "url": "https://cdn.shopify.com/s/files/1/0627/6022/2782/files/Se12519b25d2f42bc9a03237c78ef9feae.webp?v=1752125917",
                "altText": null
            },
            {
                "url": "https://cdn.shopify.com/s/files/1/0627/6022/2782/files/Sc3913d3719ed4c88adaca895b1a63c49k.webp?v=1752125917",
                "altText": null
            },
            {
                "url": "https://cdn.shopify.com/s/files/1/0627/6022/2782/files/Sc59b54bc6f9e46fba4509a79e1b77175B.webp?v=1752125917",
                "altText": null
            },
            {
                "url": "https://cdn.shopify.com/s/files/1/0627/6022/2782/files/S191822ac970a4d42a303590a4f4de13eX.webp?v=1752125917",
                "altText": null
            }
        ],
        "variants": [
            {
                "id": "41841853497406",
                "title": "Army Green",
                "sku": "14:10#Army Green",
                "price": 9.77,
                "compareAtPrice": 9.77,
                "inventory": 184
            },
            {
                "id": "41841853530174",
                "title": "Black",
                "sku": "14:350853#Black",
                "price": 9.44,
                "compareAtPrice": 9.44,
                "inventory": 171
            },
            {
                "id": "41841853562942",
                "title": "Khaki",
                "sku": "14:173#Khaki",
                "price": 10.17,
                "compareAtPrice": 10.17,
                "inventory": 98
            }
        ],
        "price": 9.77,
        "currency": "ILS",
        "syncedAt": "2025-07-10T09:49:30.352588+00:00"
    },
    {
        "_id": "7818533830718",
        "id": "7818533830718",
        "title": "60W Emergency Light Outdoor Camping Supplies Edc Outdoor USB Rechargeable LED Light Bulb Lantern Hiking Sports Entertainment",
        "description": "<h1>SPECIFICATIONS</h1><p><span>Brand Name</span>: <span style=\"color:#333\">NoEnName_Null</span></p><p><span>Choice</span>: <span style=\"color:#333\">yes</span></p><p><span>Electric</span>: <span style=\"color:#333\">Yes</span></p><p><span>Hign-concerned Chemical</span>: <span style=\"color:#333\">None</span></p><p><span>Origin</span>: <span style=\"color:#333\">Mainland China</span></p><p><span>Size</span>: <span style=\"color:#333\">S</span></p><p><span>Type</span>: <span style=\"color:#333\">Campinglight</span></p><p><span>semi_Choice</span>: <span style=\"color:#333\">yes</span></p><div class=\"detailmodule_html\"><div class=\"detail-desc-decorate-richtext\">\n<div><div>\n<p style=\"font-family:OpenSans;font-size:20px;font-weight:900;line-height:28px;white-space:pre-wrap;color:rgb(0, 0, 0);margin-bottom:12px\" class=\"detail-desc-decorate-title\">Specifications:</p>\n<div><div>\n<p style=\"font-family:OpenSans;font-size:14px;font-weight:300;line-height:20px;white-space:pre-wrap;color:rgb(0, 0, 0);margin-bottom:12px\" class=\"detail-desc-decorate-content\">Product: Waterproof lighting<br>Product material: spinning aluminum lamp body PP lamp cover<br>Product wattage: 30/60w<br>Adjust the gear position: the third gear brightness can be adjusted<br>Illumination duration: 60w (2-5h)<br>Light source chip: imported high-brightness chip<br>Light color: white<br>Lamp Bead Specifications: SMD5730<br>Working voltage: 5V, 1A<br>Applications: Emergency lights\\Night booths\\Outdoor activities, picking lights, night reading, picnic camping</p>\n<div><strong><span style=\"font-size:18px\">Features:</span></strong></div>\n<p style=\"font-family:OpenSans;font-size:14px;font-weight:300;line-height:20px;white-space:pre-wrap;color:rgb(0, 0, 0);margin-bottom:12px\" class=\"detail-desc-decorate-content\">Rechargeable light bulb, night market stall, power outage emergency, outdoor adventure<br>Brighter than the same wattage, using the sixth generation of LED chips: slow light, more power, brighter and more stable<br>More energy efficient, longer lasting power and worry<br>Long life, LED high quality lamp beads, long service life<br>High brightness, full charge can last for up to 3~6 hours (see specific properties)<br>High-energy core rapid charging, central processing system, high conversion rate<br>Same capacity, our battery life is longer<br>PP white lampshade, durable, high light transmission; resistant to falling, rainproof<br>Do you feel a lot more convenient when you buy a charging light<br>1, comes with battery, no need to pull the wire, convenient and convenient, whatever you want<br>2, power outage, outdoor camping, car breakdown, dry farm work, get a light, do whatever you want<br>3, mobile night market stalls, a light in hand, everything is free, whatever you want<br>Three-speed brightness adjustable<br>Click: highlight<br>Press again: soft light<br>Click again: strobe<br>Press again: close</p>\n</div></div>\n<p><strong><span style=\"font-size:18px\">Package included:</span></strong></p>\n<p><span style=\"font-size:16px\">1*LED lamp</span></p>\n<p><span style=\"font-size:16px\">1 x USB Cable</span><br></p>\n</div></div>\n<div>\n<div>\n<p>1.In order to ensure the service life of the product, please minimize the collision and friction.</p>\n<p>2.The product has its own waterproof function, which can prevent normal water droplet spraying, and has a built-in rechargeable battery. In order to ensure the quality of the product, please try not to touch the water erosion.<img src=\"https://ae01.alicdn.com/kf/Sc6dc5de243d34861869056c0d2127165I.jpg?width=1000&amp;height=1002&amp;hash=2002\" slate-data-type=\"image\"><img src=\"https://ae01.alicdn.com/kf/Sdf86d8e19e684349bfc76c4e423d2642R.jpg?width=1000&amp;height=1002&amp;hash=2002\" slate-data-type=\"image\">【<strong><span style=\"font-size:18px\">EASILY CARRIED</span></strong>】</p>\n</div>\n<div>\n<span style=\"font-size:16px\">Compact, lantern-like and easily portable, this dimmable LED light lantern will follow you with no more having to bring batteries everywhere is a huge relief!</span> <img src=\"https://ae01.alicdn.com/kf/Sdee9eff0858b4f39bf0a6e899ba67bbfC.jpg?width=1000&amp;height=1003&amp;hash=2003\" slate-data-type=\"image\">\n</div>\n<div>\n<img src=\"https://ae01.alicdn.com/kf/Sc4fb0eacee1b454781f583f3be6e870dL.jpg?width=1000&amp;height=1006&amp;hash=2006\" slate-data-type=\"image\"><br><img src=\"https://ae01.alicdn.com/kf/S1429e9b3726344f1a48f58eb8fb0d0802.jpg?width=1920&amp;height=1920&amp;hash=3840\" slate-data-type=\"image\"> <img src=\"https://ae01.alicdn.com/kf/Sf1f0ce63c92644389cf7628626e5920cd.jpg?width=1920&amp;height=1920&amp;hash=3840\" slate-data-type=\"image\">\n</div>\n</div>\n</div></div><p><br></p>",
        "vendor": "My Store",
        "productType": "",
        "handle": "60w-emergency-light-outdoor-camping-supplies-edc-outdoor-usb-rechargeable-led-light-bulb-lantern-hiking-sports-entertainment",
        "status": "ACTIVE",
        "tags": [],
        "images": [
            {
                "url": "https://cdn.shopify.com/s/files/1/0627/6022/2782/files/S1efa6716ca154dde9f5f38277e4fd077a.webp?v=1752125860",
                "altText": null
            },
            {
                "url": "https://cdn.shopify.com/s/files/1/0627/6022/2782/files/S070d8eec2c9444959ef6062d43895549W.webp?v=1752125860",
                "altText": null
            },
            {
                "url": "https://cdn.shopify.com/s/files/1/0627/6022/2782/files/S43149e60cf5d4ceaaa67abcd49d5b1ca3.webp?v=1752125860",
                "altText": null
            },
            {
                "url": "https://cdn.shopify.com/s/files/1/0627/6022/2782/files/Sc2f2326c78dd45d38932d6a701e2ce3cd.webp?v=1752125860",
                "altText": null
            },
            {
                "url": "https://cdn.shopify.com/s/files/1/0627/6022/2782/files/S60bb223dde1b4f68bb1f129435978e01x.webp?v=1752125860",
                "altText": null
            },
            {
                "url": "https://cdn.shopify.com/s/files/1/0627/6022/2782/files/Sc60c3704253844a7b2f4f1f9df17c0fcb.webp?v=1752125861",
                "altText": null
            },
            {
                "url": "https://cdn.shopify.com/s/files/1/0627/6022/2782/files/S379b817b41d64b49b80132b43933c765n.webp?v=1752125860",
                "altText": null
            },
            {
                "url": "https://cdn.shopify.com/s/files/1/0627/6022/2782/files/Sb55a5d9c025141cb9b209a7438804925h.webp?v=1752125861",
                "altText": null
            }
        ],
        "variants": [
            {
                "id": "41841851236414",
                "title": "30W White light",
                "sku": "14:350853#30W White light",
                "price": 11.0,
                "compareAtPrice": 11.0,
                "inventory": 175
            },
            {
                "id": "41841851269182",
                "title": "60W White light",
                "sku": "14:173#60W White light",
                "price": 11.83,
                "compareAtPrice": 11.83,
                "inventory": 272
            }
        ],
        "price": 11.0,
        "currency": "ILS",
        "syncedAt": "2025-07-10T09:49:30.352588+00:00"
    },
    {
        "_id": "7818534780990",
        "id": "7818534780990",
        "title": "60W Emergency Light Outdoor Camping Supplies Edc Outdoor USB Rechargeable LED Light Bulb Lantern Hiking Sports Entertainment",
        "description": "<h1>SPECIFICATIONS</h1><p><span>Brand Name</span>: <span style=\"color:#333\">NoEnName_Null</span></p><p><span>Choice</span>: <span style=\"color:#333\">yes</span></p><p><span>Electric</span>: <span style=\"color:#333\">Yes</span></p><p><span>Hign-concerned Chemical</span>: <span style=\"color:#333\">None</span></p><p><span>Origin</span>: <span style=\"color:#333\">Mainland China</span></p><p><span>Size</span>: <span style=\"color:#333\">S</span></p><p><span>Type</span>: <span style=\"color:#333\">Campinglight</span></p><p><span>semi_Choice</span>: <span style=\"color:#333\">yes</span></p><div class=\"detailmodule_html\"><div class=\"detail-desc-decorate-richtext\">\n<div><div>\n<p style=\"font-family:OpenSans;font-size:20px;font-weight:900;line-height:28px;white-space:pre-wrap;color:rgb(0, 0, 0);margin-bottom:12px\" class=\"detail-desc-decorate-title\">Specifications:</p>\n<div><div>\n<p style=\"font-family:OpenSans;font-size:14px;font-weight:300;line-height:20px;white-space:pre-wrap;color:rgb(0, 0, 0);margin-bottom:12px\" class=\"detail-desc-decorate-content\">Product: Waterproof lighting<br>Product material: spinning aluminum lamp body PP lamp cover<br>Product wattage: 30/60w<br>Adjust the gear position: the third gear brightness can be adjusted<br>Illumination duration: 60w (2-5h)<br>Light source chip: imported high-brightness chip<br>Light color: white<br>Lamp Bead Specifications: SMD5730<br>Working voltage: 5V, 1A<br>Applications: Emergency lights\\Night booths\\Outdoor activities, picking lights, night reading, picnic camping</p>\n<div><strong><span style=\"font-size:18px\">Features:</span></strong></div>\n<p style=\"font-family:OpenSans;font-size:14px;font-weight:300;line-height:20px;white-space:pre-wrap;color:rgb(0, 0, 0);margin-bottom:12px\" class=\"detail-desc-decorate-content\">Rechargeable light bulb, night market stall, power outage emergency, outdoor adventure<br>Brighter than the same wattage, using the sixth generation of LED chips: slow light, more power, brighter and more stable<br>More energy efficient, longer lasting power and worry<br>Long life, LED high quality lamp beads, long service life<br>High brightness, full charge can last for up to 3~6 hours (see specific properties)<br>High-energy core rapid charging, central processing system, high conversion rate<br>Same capacity, our battery life is longer<br>PP white lampshade, durable, high light transmission; resistant to falling, rainproof<br>Do you feel a lot more convenient when you buy a charging light<br>1, comes with battery, no need to pull the wire, convenient and convenient, whatever you want<br>2, power outage, outdoor camping, car breakdown, dry farm work, get a light, do whatever you want<br>3, mobile night market stalls, a light in hand, everything is free, whatever you want<br>Three-speed brightness adjustable<br>Click: highlight<br>Press again: soft light<br>Click again: strobe<br>Press again: close</p>\n</div></div>\n<p><strong><span style=\"font-size:18px\">Package included:</span></strong></p>\n<p><span style=\"font-size:16px\">1*LED lamp</span></p>\n<p><span style=\"font-size:16px\">1 x USB Cable</span><br></p>\n</div></div>\n<div>\n<div>\n<p>1.In order to ensure the service life of the product, please minimize the collision and friction.</p>\n<p>2.The product has its own waterproof function, which can prevent normal water droplet spraying, and has a built-in rechargeable battery. In order to ensure the quality of the product, please try not to touch the water erosion.<img src=\"https://ae01.alicdn.com/kf/Sc6dc5de243d34861869056c0d2127165I.jpg?width=1000&amp;height=1002&amp;hash=2002\" slate-data-type=\"image\"><img src=\"https://ae01.alicdn.com/kf/Sdf86d8e19e684349bfc76c4e423d2642R.jpg?width=1000&amp;height=1002&amp;hash=2002\" slate-data-type=\"image\">【<strong><span style=\"font-size:18px\">EASILY CARRIED</span></strong>】</p>\n</div>\n<div>\n<span style=\"font-size:16px\">Compact, lantern-like and easily portable, this dimmable LED light lantern will follow you with no more having to bring batteries everywhere is a huge relief!</span> <img src=\"https://ae01.alicdn.com/kf/Sdee9eff0858b4f39bf0a6e899ba67bbfC.jpg?width=1000&amp;height=1003&amp;hash=2003\" slate-data-type=\"image\">\n</div>\n<div>\n<img src=\"https://ae01.alicdn.com/kf/Sc4fb0eacee1b454781f583f3be6e870dL.jpg?width=1000&amp;height=1006&amp;hash=2006\" slate-data-type=\"image\"><br><img src=\"https://ae01.alicdn.com/kf/S1429e9b3726344f1a48f58eb8fb0d0802.jpg?width=1920&amp;height=1920&amp;hash=3840\" slate-data-type=\"image\"> <img src=\"https://ae01.alicdn.com/kf/Sf1f0ce63c92644389cf7628626e5920cd.jpg?width=1920&amp;height=1920&amp;hash=3840\" slate-data-type=\"image\">\n</div>\n</div>\n</div></div><p><br></p>",
        "vendor": "My Store",
        "productType": "",
        "handle": "60w-emergency-light-outdoor-camping-supplies-edc-outdoor-usb-rechargeable-led-light-bulb-lantern-hiking-sports-entertainment-1",
        "status": "ACTIVE",
        "tags": [],
        "images": [
            {
                "url": "https://cdn.shopify.com/s/files/1/0627/6022/2782/files/S1efa6716ca154dde9f5f38277e4fd077a_dc89805c-fce9-46fa-87a6-d39ef780a293.webp?v=1752125920",
                "altText": null
            },
            {
                "url": "https://cdn.shopify.com/s/files/1/0627/6022/2782/files/S070d8eec2c9444959ef6062d43895549W_7d1b10df-3595-44cc-a127-19d3ef8b16f4.webp?v=1752125919",
                "altText": null
            },
            {
                "url": "https://cdn.shopify.com/s/files/1/0627/6022/2782/files/S43149e60cf5d4ceaaa67abcd49d5b1ca3_b34a1fab-2390-4b59-8d3d-27a7f19d82b7.webp?v=1752125920",
                "altText": null
            },
            {
                "url": "https://cdn.shopify.com/s/files/1/0627/6022/2782/files/Sc2f2326c78dd45d38932d6a701e2ce3cd_060e4da0-d0fe-41e8-a784-ee38b9aa2dfe.webp?v=1752125919",
                "altText": null
            },
            {
                "url": "https://cdn.shopify.com/s/files/1/0627/6022/2782/files/S60bb223dde1b4f68bb1f129435978e01x_005b0f0a-ac94-4e59-8b28-e67f5f1de908.webp?v=1752125920",
                "altText": null
            },
            {
                "url": "https://cdn.shopify.com/s/files/1/0627/6022/2782/files/Sc60c3704253844a7b2f4f1f9df17c0fcb_1cac0e15-46c3-47f5-a6a7-22d49ef004b4.webp?v=1752125919",
                "altText": null
            },
            {
                "url": "https://cdn.shopify.com/s/files/1/0627/6022/2782/files/Sb55a5d9c025141cb9b209a7438804925h_88ea26d1-47b9-4575-967a-8fbe08b6bf45.webp?v=1752125919",
                "altText": null
            },
            {
                "url": "https://cdn.shopify.com/s/files/1/0627/6022/2782/files/S379b817b41d64b49b80132b43933c765n_a3beca79-1d31-4c63-9eca-da6c1302ba95.webp?v=1752125920",
                "altText": null
            }
        ],
        "variants": [
            {
                "id": "41841854873662",
                "title": "30W White light",
                "sku": "14:350853#30W White light",
                "price": 11.0,
                "compareAtPrice": 11.0,
                "inventory": 175
            },
            {
                "id": "41841854906430",
                "title": "60W White light",
                "sku": "14:173#60W White light",
                "price": 11.83,
                "compareAtPrice": 11.83,
                "inventory": 272
            }
        ],
        "price": 11.0,
        "currency": "ILS",
        "syncedAt": "2025-07-10T09:49:30.352588+00:00"
    },
    {
        "_id": "7818534617150",
        "id": "7818534617150",
        "title": "Camping Gas Stove Portable Folding Outdoor Backpacking Stove Tourist Equipment For Cooking Hiking Picnic 3500W",
        "description": "<h1>SPECIFICATIONS</h1><p><span>Applicable Seasoning Type</span>: <span style=\"color:#333\">Liquid Seasoning</span></p><p><span>Application Method</span>: <span style=\"color:#333\">Manual</span></p><p><span>Brand Name</span>: <span style=\"color:#333\">NoEnName_Null</span></p><p><span>Choice</span>: <span style=\"color:#333\">yes</span></p><p><span>Disposable</span>: <span style=\"color:#333\">No</span></p><p><span>Fuel</span>: <span style=\"color:#333\">Isobutane Gas Mixture</span></p><p><span>Material</span>: <span style=\"color:#333\">Stainless Steel</span></p><p><span>Number of Users</span>: <span style=\"color:#333\">&lt;3</span></p><p><span>Origin</span>: <span style=\"color:#333\">Mainland China</span></p><p><span>Piece Number Of Wind Deflector</span>: <span style=\"color:#333\">No wind shield</span></p><p><span>Structure</span>: <span style=\"color:#333\">SPLIT</span></p><p><span>Type</span>: <span style=\"color:#333\">Gas Stove</span></p><p><span>Usage Condition</span>: <span style=\"color:#333\">Normal Outdoor</span></p><p><span>With Ignition Device or Not</span>: <span style=\"color:#333\">Included</span></p><p style=\"font-family:OpenSans;font-size:20px;font-weight:900;letter-spacing:normal;line-height:28px;text-align:start;white-space:pre-wrap;color:rgb(0, 0, 0);margin:0px 0px 12px;margin-bottom:12px;margin-top:0px;margin-left:0px;margin-right:0px;padding:0px;padding-bottom:0px;padding-top:0px;padding-left:0px;padding-right:0px;box-sizing:border-box\" class=\"detail-desc-decorate-title\" align=\"start\">Product description</p><p style=\"font-family:OpenSans;font-size:14px;font-weight:300;letter-spacing:normal;line-height:20px;text-align:start;white-space:pre-wrap;color:rgb(0, 0, 0);margin:0px 0px 12px;margin-bottom:12px;margin-top:0px;margin-left:0px;margin-right:0px;padding:0px;padding-bottom:0px;padding-top:0px;padding-left:0px;padding-right:0px;box-sizing:border-box\" class=\"detail-desc-decorate-content\" align=\"start\">Name: Camping Gas burner、gas cooker<br>Material：Stainless steel copper aluminum<br>Style: outdoor、tourism、hiking、camp<br>Type: camping equipment、Camping supplies<br>Package List：1*stove 1*Plastic Box</p><p style=\"font-family:OpenSans;font-size:14px;font-weight:300;letter-spacing:normal;line-height:20px;text-align:start;white-space:pre-wrap;color:rgb(0, 0, 0);margin:0px 0px 12px;margin-bottom:12px;margin-top:0px;margin-left:0px;margin-right:0px;padding:0px;padding-bottom:0px;padding-top:0px;padding-left:0px;padding-right:0px;box-sizing:border-box\" class=\"detail-desc-decorate-content\" align=\"start\"><img src=\"https://ae01.alicdn.com/kf/S830ed75844f245f79c285a11b8caa73fK.jpg\" slate-data-type=\"image\"><img src=\"https://ae01.alicdn.com/kf/S0b2c88fce6c042079691493b37fe907f5.jpg\" slate-data-type=\"image\"><img src=\"https://ae01.alicdn.com/kf/S3bcebb37725247988be9e8d3c35ba901A.jpg\" slate-data-type=\"image\"><img src=\"https://ae01.alicdn.com/kf/Sf3f2c8f72f074ec5962165ed97da63d8K.jpg\" slate-data-type=\"image\"><img src=\"https://ae01.alicdn.com/kf/Sdde594a435494a478304053d1980576cs.jpg\" slate-data-type=\"image\"><img src=\"https://ae01.alicdn.com/kf/S55b2f4eec7c541ffb4b26766157f80666.jpg\" slate-data-type=\"image\"></p>",
        "vendor": "My Store",
        "productType": "",
        "handle": "camping-gas-stove-portable-folding-outdoor-backpacking-stove-tourist-equipment-for-cooking-hiking-picnic-3500w",
        "status": "ACTIVE",
        "tags": [],
        "images": [
            {
                "url": "https://cdn.shopify.com/s/files/1/0627/6022/2782/files/Sd236dbdb92994e3693c70f88ac2abdadN.webp?v=1752125916",
                "altText": null
            },
            {
                "url": "https://cdn.shopify.com/s/files/1/0627/6022/2782/files/Se701a381df5d492285d9a757787230ccj.webp?v=1752125916",
                "altText": null
            },
            {
                "url": "https://cdn.shopify.com/s/files/1/0627/6022/2782/files/S1d29f458d1c14cbfbaabf46c6717da7ea.webp?v=1752125916",
                "altText": null
            },
            {
                "url": "https://cdn.shopify.com/s/files/1/0627/6022/2782/files/S578f03ec8c1b4f28af513a429e35e9d6X.webp?v=1752125916",
                "altText": null
            },
            {
                "url": "https://cdn.shopify.com/s/files/1/0627/6022/2782/files/S237ed645f14c463e92bb7649a72d3893b.webp?v=1752125917",
                "altText": null
            },
            {
                "url": "https://cdn.shopify.com/s/files/1/0627/6022/2782/files/S2fce5cf3fbef4812b8278a240145fb11T.webp?v=1752125916",
                "altText": null
            },
            {
                "url": "https://cdn.shopify.com/s/files/1/0627/6022/2782/files/S6d4fc300559048b0b005f6af805f3f4fy.webp?v=1752125916",
                "altText": null
            }
        ],
        "variants": [
            {
                "id": "41841853399102",
                "title": "With adapator",
                "sku": "14:29#With adapator",
                "price": 40.44,
                "compareAtPrice": 40.44,
                "inventory": 205
            }
        ],
        "price": 40.44,
        "currency": "ILS",
        "syncedAt": "2025-07-10T09:49:30.352588+00:00"
    },
    {
        "_id": "7818534715454",
        "id": "7818534715454",
        "title": "Collapsible Folding Utility Beach Cart Wagon Heavy Duty Large Capacity Fold Wagon Ourdoor Trolley Portable Garden Camping Cart",
        "description": "<h1>SPECIFICATIONS</h1><p><span>Application</span>: <span style=\"color:#333\">Outdoor hike Garden Park wagon beach folding trolley cart Utility</span></p><p><span>Brand Name</span>: <span style=\"color:#333\">NoEnName_Null</span></p><p><span>Choice</span>: <span style=\"color:#333\">yes</span></p><p><span>Color</span>: <span style=\"color:#333\">Black</span></p><p><span>Electric</span>: <span style=\"color:#333\">No</span></p><p><span>Hign-concerned Chemical</span>: <span style=\"color:#333\">None</span></p><p><span>Material</span>: <span style=\"color:#333\">Stainless steel tubes, 600d polyester, PVC wheels</span></p><p><span>Origin</span>: <span style=\"color:#333\">Mainland China</span></p><p><span>Product Name</span>: <span style=\"color:#333\">Collapsible Folding Utility Beach Cart Wagon Heavy Duty Large Capacity Fold Wagon Ourdoor Trolley Portable Garden Camping Cart</span></p><p><span>Type</span>: <span style=\"color:#333\">Camping trolley,Heavy Duty Mover fishing beach trolley Outdoor Foldable Wagon camping</span></p><p><span>Usage</span>: <span style=\"color:#333\">Shopping, Tools, Industrial, Storage, Outdoor,Camping cart,Garden,Beach</span></p><p><span>Wheel</span>: <span style=\"color:#333\">Four-wheel</span></p><p><span style=\"color:rgb(255, 255, 255);font-size:12px\">Capacity 500lbs Heavy Duty Foldable Wagon<br> Shopping Beach Garden Pull Trolley Collapsible Folding Outdoor Portable Utility Cart Shopping Beach Garden Pull Trolley Collapsible Folding Outdoor Portable Utility Cart Heavy Duty Large Capacity Folding Wagon</span></p><p><img width=\"900\" height=\"900\" src=\"https://ae01.alicdn.com/kf/S322dcf41d6cf4482b2395c97203047e85.jpg\" slate-data-type=\"image\"></p><p><img width=\"900\" height=\"900\" src=\"https://ae01.alicdn.com/kf/S0c1c55518cbf4f9389ddece02dc02986k.jpg\" slate-data-type=\"image\"></p><p><img src=\"https://ae01.alicdn.com/kf/Sed48218bb5a6492690648ee3eaa66c0ex.jpg\" slate-data-type=\"image\"></p><p><img src=\"https://ae01.alicdn.com/kf/S410b53f3ebc64ff28ca5e8681f229f83A.jpg\" slate-data-type=\"image\"></p><p><img src=\"https://ae01.alicdn.com/kf/S0ec58ce665404b308d3038083ed58751J.jpg\" slate-data-type=\"image\"><img src=\"https://ae01.alicdn.com/kf/S4d541f066e2844debda28491f3cc185c9.jpg\" slate-data-type=\"image\"></p><p><img src=\"https://ae01.alicdn.com/kf/Sac768fcc42934868af31658cf0e227f27.jpg\" slate-data-type=\"image\"></p><p><img src=\"https://ae01.alicdn.com/kf/S36864d2a9a8d4c82812fd8415097311bl.jpg\" slate-data-type=\"image\"></p><p><br></p><p><img src=\"https://ae01.alicdn.com/kf/S1c5fc64b35ee409b832d67862c5eb9b6m.jpg\" slate-data-type=\"image\"></p><p><img src=\"https://ae01.alicdn.com/kf/Sb8c49092c31040cd8e2bd71afb366f3eU.jpg\" slate-data-type=\"image\"></p><p><img src=\"https://ae01.alicdn.com/kf/Sfad5f036b7d34db69e74a428a13b92278.jpg\" slate-data-type=\"image\"><img src=\"https://ae01.alicdn.com/kf/Scb8e6a23ea9e4e67ad88d2b48135c0e2Q.jpg\" slate-data-type=\"image\"><img src=\"https://ae01.alicdn.com/kf/S5e91aa38f77a4e5db2d651c2e454c424d.jpg\" slate-data-type=\"image\"><img src=\"https://ae01.alicdn.com/kf/Sa646ef21c7854ef6a3b4252bbad486e0D.jpg\" slate-data-type=\"image\"><img src=\"https://ae01.alicdn.com/kf/Sfbaea1b400a948b29e56b23880003cc65.jpg\" slate-data-type=\"image\"><img src=\"https://ae01.alicdn.com/kf/Sf34a0cfcd0b14d0e8bd3c4b19eeb35ebC.jpg\" slate-data-type=\"image\"><img src=\"https://ae01.alicdn.com/kf/S38f6dd7519b94842979625e559205bf2T.jpg\" slate-data-type=\"image\"><img src=\"https://ae01.alicdn.com/kf/S710354ec896b4510a2e59954b5a696f9m.jpg\" slate-data-type=\"image\"><img src=\"https://ae01.alicdn.com/kf/S08c9f3b71b4b4a3095d2fc2d0eb60820E.jpg\" slate-data-type=\"image\"><img src=\"https://ae01.alicdn.com/kf/S1b4f9345829f4369a690ff17e598dfb99.jpg\" slate-data-type=\"image\"><img src=\"https://ae01.alicdn.com/kf/Sdf910aaf6711473bb2a9f83b4b026ca30.jpg\" slate-data-type=\"image\"><img src=\"https://ae01.alicdn.com/kf/S4f83f8adb12e4da5b4b79f60191199ddI.jpg\" slate-data-type=\"image\"><img src=\"https://ae01.alicdn.com/kf/S42617ff313264143b3a34b727339119eo.jpg\" slate-data-type=\"image\"><img src=\"https://ae01.alicdn.com/kf/S87962435f9494e0f80904039948d32d39.jpg\" slate-data-type=\"image\"></p>",
        "vendor": "My Store",
        "productType": "",
        "handle": "collapsible-folding-utility-beach-cart-wagon-heavy-duty-large-capacity-fold-wagon-ourdoor-trolley-portable-garden-camping-cart",
        "status": "ACTIVE",
        "tags": [],
        "images": [
            {
                "url": "https://cdn.shopify.com/s/files/1/0627/6022/2782/files/S356a34423f314c7bb7995a277087d57ex.webp?v=1752125918",
                "altText": null
            },
            {
                "url": "https://cdn.shopify.com/s/files/1/0627/6022/2782/files/Sfa41328c9e304675a2be85efad29c4b5f.webp?v=1752125918",
                "altText": null
            },
            {
                "url": "https://cdn.shopify.com/s/files/1/0627/6022/2782/files/S06c5e4a7ab8646ba92081c79cae51254X.webp?v=1752125918",
                "altText": null
            },
            {
                "url": "https://cdn.shopify.com/s/files/1/0627/6022/2782/files/S6adb5ec1df7445aeb93a8f19149d321dO.webp?v=1752125918",
                "altText": null
            },
            {
                "url": "https://cdn.shopify.com/s/files/1/0627/6022/2782/files/S0c4a37a0e2004717a08781ed6bd3606eA.webp?v=1752125918",
                "altText": null
            },
            {
                "url": "https://cdn.shopify.com/s/files/1/0627/6022/2782/files/Sc12ca6510a7f424da3fc220d49834593p.webp?v=1752125919",
                "altText": null
            },
            {
                "url": "https://cdn.shopify.com/s/files/1/0627/6022/2782/files/Sccbaa5a30aa64d5bbcd2d563059b72699.webp?v=1752125918",
                "altText": null
            },
            {
                "url": "https://cdn.shopify.com/s/files/1/0627/6022/2782/files/Sf095a64010c74f7ca75c7bccbb6e71804.webp?v=1752125918",
                "altText": null
            },
            {
                "url": "https://cdn.shopify.com/s/files/1/0627/6022/2782/files/See3b0a7fd23b49868626c6db97a49cfei.webp?v=1752125918",
                "altText": null
            },
            {
                "url": "https://cdn.shopify.com/s/files/1/0627/6022/2782/files/S4d23067b508647d9a73cb22d70c7ee3fq.webp?v=1752125918",
                "altText": null
            },
            {
                "url": "https://cdn.shopify.com/s/files/1/0627/6022/2782/files/S2345a2d1240a4efb866fb618630f2251N.webp?v=1752125918",
                "altText": null
            },
            {
                "url": "https://cdn.shopify.com/s/files/1/0627/6022/2782/files/S4af293b8f5b942118e9d68b991f38726z.webp?v=1752125918",
                "altText": null
            }
        ],
        "variants": [
            {
                "id": "41841853661246",
                "title": "STC8-3-mika",
                "sku": "14:193#STC8-3-mika",
                "price": 276.57,
                "compareAtPrice": 276.57,
                "inventory": 272
            },
            {
                "id": "41841853694014",
                "title": "ZB-upgrade",
                "sku": "14:10#ZB-upgrade",
                "price": 119.33,
                "compareAtPrice": 119.33,
                "inventory": 268
            },
            {
                "id": "41841853726782",
                "title": "STC220LBS",
                "sku": "14:173#STC220LBS",
                "price": 156.11,
                "compareAtPrice": 156.11,
                "inventory": 392
            },
            {
                "id": "41841853759550",
                "title": "ZB-normal",
                "sku": "14:175#ZB-normal",
                "price": 99.62,
                "compareAtPrice": 99.62,
                "inventory": 52
            },
            {
                "id": "41841853792318",
                "title": "STC500LBS",
                "sku": "14:350853#STC500LBS",
                "price": 280.59,
                "compareAtPrice": 280.59,
                "inventory": 625
            },
            {
                "id": "41841853825086",
                "title": "STC220LBS-mika",
                "sku": "14:366#STC220LBS-mika",
                "price": 165.12,
                "compareAtPrice": 165.12,
                "inventory": 85
            }
        ],
        "price": 276.57,
        "currency": "ILS",
        "syncedAt": "2025-07-10T09:49:30.352588+00:00"
    },
    {
        "_id": "7818534355006",
        "id": "7818534355006",
        "title": "Military 550 Paracord Rope 100M 50M 31M 7 Strand 4mm Parachute Cord Outdoor Camping Survival Gear DIY Bracelet Tent Line",
        "description": "<h1>SPECIFICATIONS</h1><p><span>Brand Name</span>: <span style=\"color:#333\">Noble Eagle</span></p><p><span>Choice</span>: <span style=\"color:#333\">yes</span></p><p><span>Diameter</span>: <span style=\"color:#333\">4MM</span></p><p><span>Hign-concerned Chemical</span>: <span style=\"color:#333\">None</span></p><p><span>Length</span>: <span style=\"color:#333\">100 M (328FT)</span></p><p><span>Material</span>: <span style=\"color:#333\">polypropylene fiber</span></p><p><span>Number of strand</span>: <span style=\"color:#333\">7</span></p><p><span>Origin</span>: <span style=\"color:#333\">Mainland China</span></p><p><span>semi_Choice</span>: <span style=\"color:#333\">yes</span></p><div class=\"detailmodule_text\">\n<p style=\"font-family:OpenSans;font-size:20px;font-weight:900;line-height:28px;white-space:pre-wrap;color:rgb(0, 0, 0);margin-bottom:12px\" class=\"detail-desc-decorate-title\">550 Paracord - 7 Strands</p>\n<p style=\"font-family:OpenSans;font-size:14px;font-weight:300;line-height:20px;white-space:pre-wrap;color:rgb(0, 0, 0);margin-bottom:12px\" class=\"detail-desc-decorate-content\">・7-core paracord<br>・550 military standard<br>・4MM diameter, maximum load 550LB</p>\n</div><div class=\"detailmodule_text\">\n<p style=\"font-family:OpenSans;font-size:20px;font-weight:900;line-height:28px;white-space:pre-wrap;color:rgb(0, 0, 0);margin-bottom:12px\" class=\"detail-desc-decorate-title\">Specification</p>\n<p style=\"font-family:OpenSans;font-size:14px;font-weight:300;line-height:20px;white-space:pre-wrap;color:rgb(0, 0, 0);margin-bottom:12px\" class=\"detail-desc-decorate-content\">Material: Polypropylene/Polyester<br>Standard: 550 military standard<br>Rope standard: 7 inner strands<br>Length: 100M (330FT) / Axis<br>Diameter: 4mm<br>Maximum load: 550LB（249KG）<br>Weight: about 500g</p>\n</div><div class=\"detailmodule_text\">\n<p style=\"font-family:OpenSans;font-size:20px;font-weight:900;line-height:28px;white-space:pre-wrap;color:rgb(0, 0, 0);margin-bottom:12px\" class=\"detail-desc-decorate-title\">USE</p>\n<p style=\"font-family:OpenSans;font-size:14px;font-weight:300;line-height:20px;white-space:pre-wrap;color:rgb(0, 0, 0);margin-bottom:12px\" class=\"detail-desc-decorate-content\">・ An important outdoor tool.<br>Such as (outdoor temporary) simple housing construction; repairing equipment and clothing; making traps and fishing nets; making fire bows, etc.<br>・ Umbrella rope art.<br>The umbrella rope is woven into pendants, bracelets, belts, backpacks and other items through a certain weaving method, which is more convenient for carrying around. Convenient for outdoor use.<br>・ Used as a pet collar, traction knitting,<br>Sturdy and durable, pets are more comfortable to wear than leashes and iron chains.</p>\n</div><div class=\"detailmodule_text-image\"><img style=\"margin-bottom:10px\" class=\"detail-desc-decorate-image\" src=\"https://ae01.alicdn.com/kf/Scf76245b20684913a8179ba0ff7593a7j.jpg\" slate-data-type=\"image\"></div><div class=\"detailmodule_text-image\">\n<img class=\"detail-desc-decorate-image\" src=\"https://ae03.alicdn.com/kf/S97a227e06523417d8b2cf705dddfc8b3a.jpg\" slate-data-type=\"image\"><img class=\"detail-desc-decorate-image\" src=\"https://ae03.alicdn.com/kf/Hd6f934dcdedf4ebca501122d5a23a822j.jpg\" slate-data-type=\"image\"><img class=\"detail-desc-decorate-image\" src=\"https://ae03.alicdn.com/kf/H36074f2da248453d930beb9e8115f90cB.jpg\" slate-data-type=\"image\"><img class=\"detail-desc-decorate-image\" src=\"https://ae03.alicdn.com/kf/H37e64612c492469aac049ef3dc38a5f3A.jpg\" slate-data-type=\"image\"><img class=\"detail-desc-decorate-image\" src=\"https://ae03.alicdn.com/kf/Hfd1c16fb9bae48108e62b63c39cd68eer.jpg\" slate-data-type=\"image\"><img class=\"detail-desc-decorate-image\" src=\"https://ae03.alicdn.com/kf/H8c0547fa813343e1b2fbde6da96e1ab7B.jpg\" slate-data-type=\"image\"><img class=\"detail-desc-decorate-image\" src=\"https://ae03.alicdn.com/kf/H34e9de12ad4d407ab3d4212a546dd5e2C.jpg\" slate-data-type=\"image\"><img class=\"detail-desc-decorate-image\" src=\"https://ae03.alicdn.com/kf/H08ec179cc4a2451a918c8b77f926ac53X.jpg\" slate-data-type=\"image\"><img class=\"detail-desc-decorate-image\" src=\"https://ae03.alicdn.com/kf/Hc0871fd45a114d6fa0312d94700db64ee.jpg\" slate-data-type=\"image\"><img class=\"detail-desc-decorate-image\" src=\"https://ae03.alicdn.com/kf/H97801aef6abb4f489db2bafd14686b4co.jpg\" slate-data-type=\"image\">\n</div><div class=\"detailmodule_text-image\">\n<img class=\"detail-desc-decorate-image\" src=\"https://ae01.alicdn.com/kf/Sea5e48ada63b42b28e9f00d79bbbf69ay.jpg\" slate-data-type=\"image\"><img class=\"detail-desc-decorate-image\" src=\"https://ae01.alicdn.com/kf/S58f0e875d1d54ef6b0152e99423ad7463.jpg\" slate-data-type=\"image\"><img class=\"detail-desc-decorate-image\" src=\"https://ae01.alicdn.com/kf/S1efb47b43c9547f587206c860bf8d1deo.jpg\" slate-data-type=\"image\"><img class=\"detail-desc-decorate-image\" src=\"https://ae01.alicdn.com/kf/S240f5e5c0b28454db1b92d9e427fb893B.jpg\" slate-data-type=\"image\"><img class=\"detail-desc-decorate-image\" src=\"https://ae01.alicdn.com/kf/Sbc3e076d03f94b168845a6fc346ae75fA.jpg\" slate-data-type=\"image\"><img class=\"detail-desc-decorate-image\" src=\"https://ae01.alicdn.com/kf/Se18dc07ef89b459c846da75fc7eb0e00F.jpg\" slate-data-type=\"image\"><img class=\"detail-desc-decorate-image\" src=\"https://ae01.alicdn.com/kf/S3727d58e028145ef8431366e9a1b15dcF.jpg\" slate-data-type=\"image\"><img class=\"detail-desc-decorate-image\" src=\"https://ae01.alicdn.com/kf/S659e01cee39b4e65a98f31c6ad4c6ad2T.jpg\" slate-data-type=\"image\"><img class=\"detail-desc-decorate-image\" src=\"https://ae01.alicdn.com/kf/Se189921dd1714225841d3e6a30a62065d.jpg\" slate-data-type=\"image\"><img class=\"detail-desc-decorate-image\" src=\"https://ae01.alicdn.com/kf/Sed30f46644fc4d1c923ee8e9311513f2q.jpg\" slate-data-type=\"image\">\n</div><p><br></p>",
        "vendor": "My Store",
        "productType": "",
        "handle": "military-550-paracord-rope-100m-50m-31m-7-strand-4mm-parachute-cord-outdoor-camping-survival-gear-diy-bracelet-tent-line",
        "status": "ACTIVE",
        "tags": [],
        "images": [
            {
                "url": "https://cdn.shopify.com/s/files/1/0627/6022/2782/files/Scf76245b20684913a8179ba0ff7593a7j.webp?v=1752125895",
                "altText": null
            },
            {
                "url": "https://cdn.shopify.com/s/files/1/0627/6022/2782/files/Sb8f6c0394a5249bfa425b08620a2b94dx.webp?v=1752125895",
                "altText": null
            },
            {
                "url": "https://cdn.shopify.com/s/files/1/0627/6022/2782/files/Sb395cbd535334bbb963e691baa229aee7.webp?v=1752125895",
                "altText": null
            },
            {
                "url": "https://cdn.shopify.com/s/files/1/0627/6022/2782/files/S503cc82970e24d02a2d635fbbe1cfc407.webp?v=1752125895",
                "altText": null
            },
            {
                "url": "https://cdn.shopify.com/s/files/1/0627/6022/2782/files/Sa512037919644e249de3c51a6f89f349A.webp?v=1752125895",
                "altText": null
            },
            {
                "url": "https://cdn.shopify.com/s/files/1/0627/6022/2782/files/S131a940ffe9047d6a88b1ff80584c96f0.webp?v=1752125895",
                "altText": null
            },
            {
                "url": "https://cdn.shopify.com/s/files/1/0627/6022/2782/files/Sed30f46644fc4d1c923ee8e9311513f2q.webp?v=1752125895",
                "altText": null
            },
            {
                "url": "https://cdn.shopify.com/s/files/1/0627/6022/2782/files/S1efb47b43c9547f587206c860bf8d1deo.webp?v=1752125895",
                "altText": null
            },
            {
                "url": "https://cdn.shopify.com/s/files/1/0627/6022/2782/files/Sbc3e076d03f94b168845a6fc346ae75fA.webp?v=1752125895",
                "altText": null
            },
            {
                "url": "https://cdn.shopify.com/s/files/1/0627/6022/2782/files/S58f0e875d1d54ef6b0152e99423ad7463.webp?v=1752125896",
                "altText": null
            },
            {
                "url": "https://cdn.shopify.com/s/files/1/0627/6022/2782/files/Sea5e48ada63b42b28e9f00d79bbbf69ay.webp?v=1752125895",
                "altText": null
            },
            {
                "url": "https://cdn.shopify.com/s/files/1/0627/6022/2782/files/S3727d58e028145ef8431366e9a1b15dcF.webp?v=1752125895",
                "altText": null
            },
            {
                "url": "https://cdn.shopify.com/s/files/1/0627/6022/2782/files/Se189921dd1714225841d3e6a30a62065d.webp?v=1752125895",
                "altText": null
            },
            {
                "url": "https://cdn.shopify.com/s/files/1/0627/6022/2782/files/Se18dc07ef89b459c846da75fc7eb0e00F.webp?v=1752125895",
                "altText": null
            },
            {
                "url": "https://cdn.shopify.com/s/files/1/0627/6022/2782/files/S240f5e5c0b28454db1b92d9e427fb893B.webp?v=1752125895",
                "altText": null
            },
            {
                "url": "https://cdn.shopify.com/s/files/1/0627/6022/2782/files/S659e01cee39b4e65a98f31c6ad4c6ad2T.webp?v=1752125895",
                "altText": null
            }
        ],
        "variants": [
            {
                "id": "41841851859006",
                "title": "7C Orange / 100M",
                "sku": "14:173#7C Orange;200085263:200007633#100M",
                "price": 46.29,
                "compareAtPrice": 46.29,
                "inventory": 19
            },
            {
                "id": "41841851891774",
                "title": "7C Army green / 50M",
                "sku": "14:10#7C Army green;200085263:200007637#50M",
                "price": 25.42,
                "compareAtPrice": 25.42,
                "inventory": 28
            },
            {
                "id": "41841851924542",
                "title": "7C Brown / 100M",
                "sku": "14:175#7C Brown;200085263:200007633#100M",
                "price": 46.26,
                "compareAtPrice": 46.26,
                "inventory": 26
            },
            {
                "id": "41841851957310",
                "title": "7C Orange / 50M",
                "sku": "14:173#7C Orange;200085263:200007637#50M",
                "price": 24.12,
                "compareAtPrice": 24.12,
                "inventory": 11
            },
            {
                "id": "41841851990078",
                "title": "7C Black / 100M",
                "sku": "14:350853#7C Black;200085263:200007633#100M",
                "price": 46.42,
                "compareAtPrice": 46.42,
                "inventory": 67
            },
            {
                "id": "41841852022846",
                "title": "7C Army green / 100M",
                "sku": "14:10#7C Army green;200085263:200007633#100M",
                "price": 46.06,
                "compareAtPrice": 46.06,
                "inventory": 21
            },
            {
                "id": "41841852055614",
                "title": "7C Black / 50M",
                "sku": "14:350853#7C Black;200085263:200007637#50M",
                "price": 24.49,
                "compareAtPrice": 24.49,
                "inventory": 44
            },
            {
                "id": "41841852088382",
                "title": "7C Camouflage / 100M",
                "sku": "14:201618806#7C Camouflage;200085263:200007633#100M",
                "price": 45.52,
                "compareAtPrice": 45.52,
                "inventory": 22
            },
            {
                "id": "41841852121150",
                "title": "7C Red / 50M",
                "sku": "14:366#7C Red;200085263:200007637#50M",
                "price": 24.29,
                "compareAtPrice": 24.29,
                "inventory": 25
            },
            {
                "id": "41841852153918",
                "title": "7C Red Camouflage / 100M",
                "sku": "14:350686#7C Red Camouflage;200085263:200007633#100M",
                "price": 45.66,
                "compareAtPrice": 45.66,
                "inventory": 22
            },
            {
                "id": "41841852186686",
                "title": "7C Camouflage / 50M",
                "sku": "14:201618806#7C Camouflage;200085263:200007637#50M",
                "price": 23.99,
                "compareAtPrice": 23.99,
                "inventory": 16
            },
            {
                "id": "41841852219454",
                "title": "7C Blue / 100M",
                "sku": "14:193#7C Blue;200085263:200007633#100M",
                "price": 45.36,
                "compareAtPrice": 45.36,
                "inventory": 21
            },
            {
                "id": "41841852252222",
                "title": "7C Brown / 50M",
                "sku": "14:175#7C Brown;200085263:200007637#50M",
                "price": 24.39,
                "compareAtPrice": 24.39,
                "inventory": 14
            },
            {
                "id": "41841852284990",
                "title": "7C Red / 100M",
                "sku": "14:366#7C Red;200085263:200007633#100M",
                "price": 46.02,
                "compareAtPrice": 46.02,
                "inventory": 28
            },
            {
                "id": "41841852317758",
                "title": "7C Blue / 50M",
                "sku": "14:193#7C Blue;200085263:200007637#50M",
                "price": 25.12,
                "compareAtPrice": 25.12,
                "inventory": 18
            },
            {
                "id": "41841852350526",
                "title": "7C Orange Camouflage / 31M",
                "sku": "14:200572156#7C Orange Camouflage;200085263:4#31M",
                "price": 16.61,
                "compareAtPrice": 16.61,
                "inventory": 23
            },
            {
                "id": "41841852383294",
                "title": "7C Deserts / 50M",
                "sku": "14:350852#7C Deserts;200085263:200007637#50M",
                "price": 23.99,
                "compareAtPrice": 23.99,
                "inventory": 15
            },
            {
                "id": "41841852416062",
                "title": "7C Deserts / 31M",
                "sku": "14:350852#7C Deserts;200085263:4#31M",
                "price": 16.48,
                "compareAtPrice": 16.48,
                "inventory": 30
            },
            {
                "id": "41841852448830",
                "title": "7C Orange Camouflage / 100M",
                "sku": "14:200572156#7C Orange Camouflage;200085263:200007633#100M",
                "price": 46.26,
                "compareAtPrice": 46.26,
                "inventory": 13
            },
            {
                "id": "41841852481598",
                "title": "7C Red Camouflage / 50M",
                "sku": "14:350686#7C Red Camouflage;200085263:200007637#50M",
                "price": 24.12,
                "compareAtPrice": 24.12,
                "inventory": 20
            },
            {
                "id": "41841852514366",
                "title": "7C Deserts / 100M",
                "sku": "14:350852#7C Deserts;200085263:200007633#100M",
                "price": 45.72,
                "compareAtPrice": 45.72,
                "inventory": 28
            },
            {
                "id": "41841852547134",
                "title": "7C Orange Camouflage / 50M",
                "sku": "14:200572156#7C Orange Camouflage;200085263:200007637#50M",
                "price": 24.39,
                "compareAtPrice": 24.39,
                "inventory": 12
            },
            {
                "id": "41841852579902",
                "title": "7C Black / 31M",
                "sku": "14:350853#7C Black;200085263:4#31M",
                "price": 16.71,
                "compareAtPrice": 16.71,
                "inventory": 51
            },
            {
                "id": "41841852612670",
                "title": "7C Army green / 31M",
                "sku": "14:10#7C Army green;200085263:4#31M",
                "price": 15.78,
                "compareAtPrice": 15.78,
                "inventory": 37
            },
            {
                "id": "41841852645438",
                "title": "7C Orange / 31M",
                "sku": "14:173#7C Orange;200085263:4#31M",
                "price": 16.42,
                "compareAtPrice": 16.42,
                "inventory": 16
            },
            {
                "id": "41841852678206",
                "title": "7C Brown / 31M",
                "sku": "14:175#7C Brown;200085263:4#31M",
                "price": 16.25,
                "compareAtPrice": 16.25,
                "inventory": 25
            },
            {
                "id": "41841852710974",
                "title": "7C Blue / 31M",
                "sku": "14:193#7C Blue;200085263:4#31M",
                "price": 16.52,
                "compareAtPrice": 16.52,
                "inventory": 4
            },
            {
                "id": "41841852743742",
                "title": "7C Red / 31M",
                "sku": "14:366#7C Red;200085263:4#31M",
                "price": 16.52,
                "compareAtPrice": 16.52,
                "inventory": 18
            },
            {
                "id": "41841852776510",
                "title": "7C Camouflage / 31M",
                "sku": "14:201618806#7C Camouflage;200085263:4#31M",
                "price": 16.52,
                "compareAtPrice": 16.52,
                "inventory": 30
            },
            {
                "id": "41841852809278",
                "title": "7C Red Camouflage / 31M",
                "sku": "14:350686#7C Red Camouflage;200085263:4#31M",
                "price": 16.52,
                "compareAtPrice": 16.52,
                "inventory": 68
            }
        ],
        "price": 46.29,
        "currency": "ILS",
        "syncedAt": "2025-07-10T09:49:30.353587+00:00"
    },
    {
        "_id": "7818534748222",
        "id": "7818534748222",
        "title": "Military 550 Paracord Rope 100M 50M 31M 7 Strand 4mm Parachute Cord Outdoor Camping Survival Gear DIY Bracelet Tent Line",
        "description": "<h1>SPECIFICATIONS</h1><p><span>Brand Name</span>: <span style=\"color:#333\">Noble Eagle</span></p><p><span>Choice</span>: <span style=\"color:#333\">yes</span></p><p><span>Diameter</span>: <span style=\"color:#333\">4MM</span></p><p><span>Hign-concerned Chemical</span>: <span style=\"color:#333\">None</span></p><p><span>Length</span>: <span style=\"color:#333\">100 M (328FT)</span></p><p><span>Material</span>: <span style=\"color:#333\">polypropylene fiber</span></p><p><span>Number of strand</span>: <span style=\"color:#333\">7</span></p><p><span>Origin</span>: <span style=\"color:#333\">Mainland China</span></p><p><span>semi_Choice</span>: <span style=\"color:#333\">yes</span></p><div class=\"detailmodule_text\">\n<p style=\"font-family:OpenSans;font-size:20px;font-weight:900;line-height:28px;white-space:pre-wrap;color:rgb(0, 0, 0);margin-bottom:12px\" class=\"detail-desc-decorate-title\">550 Paracord - 7 Strands</p>\n<p style=\"font-family:OpenSans;font-size:14px;font-weight:300;line-height:20px;white-space:pre-wrap;color:rgb(0, 0, 0);margin-bottom:12px\" class=\"detail-desc-decorate-content\">・7-core paracord<br>・550 military standard<br>・4MM diameter, maximum load 550LB</p>\n</div><div class=\"detailmodule_text\">\n<p style=\"font-family:OpenSans;font-size:20px;font-weight:900;line-height:28px;white-space:pre-wrap;color:rgb(0, 0, 0);margin-bottom:12px\" class=\"detail-desc-decorate-title\">Specification</p>\n<p style=\"font-family:OpenSans;font-size:14px;font-weight:300;line-height:20px;white-space:pre-wrap;color:rgb(0, 0, 0);margin-bottom:12px\" class=\"detail-desc-decorate-content\">Material: Polypropylene/Polyester<br>Standard: 550 military standard<br>Rope standard: 7 inner strands<br>Length: 100M (330FT) / Axis<br>Diameter: 4mm<br>Maximum load: 550LB（249KG）<br>Weight: about 500g</p>\n</div><div class=\"detailmodule_text\">\n<p style=\"font-family:OpenSans;font-size:20px;font-weight:900;line-height:28px;white-space:pre-wrap;color:rgb(0, 0, 0);margin-bottom:12px\" class=\"detail-desc-decorate-title\">USE</p>\n<p style=\"font-family:OpenSans;font-size:14px;font-weight:300;line-height:20px;white-space:pre-wrap;color:rgb(0, 0, 0);margin-bottom:12px\" class=\"detail-desc-decorate-content\">・ An important outdoor tool.<br>Such as (outdoor temporary) simple housing construction; repairing equipment and clothing; making traps and fishing nets; making fire bows, etc.<br>・ Umbrella rope art.<br>The umbrella rope is woven into pendants, bracelets, belts, backpacks and other items through a certain weaving method, which is more convenient for carrying around. Convenient for outdoor use.<br>・ Used as a pet collar, traction knitting,<br>Sturdy and durable, pets are more comfortable to wear than leashes and iron chains.</p>\n</div><div class=\"detailmodule_text-image\"><img style=\"margin-bottom:10px\" class=\"detail-desc-decorate-image\" src=\"https://ae01.alicdn.com/kf/Scf76245b20684913a8179ba0ff7593a7j.jpg\" slate-data-type=\"image\"></div><div class=\"detailmodule_text-image\">\n<img class=\"detail-desc-decorate-image\" src=\"https://ae03.alicdn.com/kf/S97a227e06523417d8b2cf705dddfc8b3a.jpg\" slate-data-type=\"image\"><img class=\"detail-desc-decorate-image\" src=\"https://ae03.alicdn.com/kf/Hd6f934dcdedf4ebca501122d5a23a822j.jpg\" slate-data-type=\"image\"><img class=\"detail-desc-decorate-image\" src=\"https://ae03.alicdn.com/kf/H36074f2da248453d930beb9e8115f90cB.jpg\" slate-data-type=\"image\"><img class=\"detail-desc-decorate-image\" src=\"https://ae03.alicdn.com/kf/H37e64612c492469aac049ef3dc38a5f3A.jpg\" slate-data-type=\"image\"><img class=\"detail-desc-decorate-image\" src=\"https://ae03.alicdn.com/kf/Hfd1c16fb9bae48108e62b63c39cd68eer.jpg\" slate-data-type=\"image\"><img class=\"detail-desc-decorate-image\" src=\"https://ae03.alicdn.com/kf/H8c0547fa813343e1b2fbde6da96e1ab7B.jpg\" slate-data-type=\"image\"><img class=\"detail-desc-decorate-image\" src=\"https://ae03.alicdn.com/kf/H34e9de12ad4d407ab3d4212a546dd5e2C.jpg\" slate-data-type=\"image\"><img class=\"detail-desc-decorate-image\" src=\"https://ae03.alicdn.com/kf/H08ec179cc4a2451a918c8b77f926ac53X.jpg\" slate-data-type=\"image\"><img class=\"detail-desc-decorate-image\" src=\"https://ae03.alicdn.com/kf/Hc0871fd45a114d6fa0312d94700db64ee.jpg\" slate-data-type=\"image\"><img class=\"detail-desc-decorate-image\" src=\"https://ae03.alicdn.com/kf/H97801aef6abb4f489db2bafd14686b4co.jpg\" slate-data-type=\"image\">\n</div><div class=\"detailmodule_text-image\">\n<img class=\"detail-desc-decorate-image\" src=\"https://ae01.alicdn.com/kf/Sea5e48ada63b42b28e9f00d79bbbf69ay.jpg\" slate-data-type=\"image\"><img class=\"detail-desc-decorate-image\" src=\"https://ae01.alicdn.com/kf/S58f0e875d1d54ef6b0152e99423ad7463.jpg\" slate-data-type=\"image\"><img class=\"detail-desc-decorate-image\" src=\"https://ae01.alicdn.com/kf/S1efb47b43c9547f587206c860bf8d1deo.jpg\" slate-data-type=\"image\"><img class=\"detail-desc-decorate-image\" src=\"https://ae01.alicdn.com/kf/S240f5e5c0b28454db1b92d9e427fb893B.jpg\" slate-data-type=\"image\"><img class=\"detail-desc-decorate-image\" src=\"https://ae01.alicdn.com/kf/Sbc3e076d03f94b168845a6fc346ae75fA.jpg\" slate-data-type=\"image\"><img class=\"detail-desc-decorate-image\" src=\"https://ae01.alicdn.com/kf/Se18dc07ef89b459c846da75fc7eb0e00F.jpg\" slate-data-type=\"image\"><img class=\"detail-desc-decorate-image\" src=\"https://ae01.alicdn.com/kf/S3727d58e028145ef8431366e9a1b15dcF.jpg\" slate-data-type=\"image\"><img class=\"detail-desc-decorate-image\" src=\"https://ae01.alicdn.com/kf/S659e01cee39b4e65a98f31c6ad4c6ad2T.jpg\" slate-data-type=\"image\"><img class=\"detail-desc-decorate-image\" src=\"https://ae01.alicdn.com/kf/Se189921dd1714225841d3e6a30a62065d.jpg\" slate-data-type=\"image\"><img class=\"detail-desc-decorate-image\" src=\"https://ae01.alicdn.com/kf/Sed30f46644fc4d1c923ee8e9311513f2q.jpg\" slate-data-type=\"image\">\n</div><p><br></p>",
        "vendor": "My Store",
        "productType": "",
        "handle": "military-550-paracord-rope-100m-50m-31m-7-strand-4mm-parachute-cord-outdoor-camping-survival-gear-diy-bracelet-tent-line-1",
        "status": "ACTIVE",
        "tags": [],
        "images": [
            {
                "url": "https://cdn.shopify.com/s/files/1/0627/6022/2782/files/Scf76245b20684913a8179ba0ff7593a7j_f51ffc43-0554-47ab-8c8e-8eb2e8dfd1bc.webp?v=1752125920",
                "altText": null
            },
            {
                "url": "https://cdn.shopify.com/s/files/1/0627/6022/2782/files/Sb8f6c0394a5249bfa425b08620a2b94dx_f3a1e866-6c01-40f2-acf0-ee61aa61e986.webp?v=1752125920",
                "altText": null
            },
            {
                "url": "https://cdn.shopify.com/s/files/1/0627/6022/2782/files/Sb395cbd535334bbb963e691baa229aee7_daadb86d-1d4e-4ac6-aec2-b4a429b1308f.webp?v=1752125920",
                "altText": null
            },
            {
                "url": "https://cdn.shopify.com/s/files/1/0627/6022/2782/files/S503cc82970e24d02a2d635fbbe1cfc407_1e2b4860-adb5-4b8a-82c6-063348dfdda8.webp?v=1752125920",
                "altText": null
            },
            {
                "url": "https://cdn.shopify.com/s/files/1/0627/6022/2782/files/Sa512037919644e249de3c51a6f89f349A_7477a958-de20-4a75-9ef8-69956c95a6fa.webp?v=1752125920",
                "altText": null
            },
            {
                "url": "https://cdn.shopify.com/s/files/1/0627/6022/2782/files/S131a940ffe9047d6a88b1ff80584c96f0_d96b5aa8-9cc7-4572-ad96-b6a5149b65e1.webp?v=1752125920",
                "altText": null
            },
            {
                "url": "https://cdn.shopify.com/s/files/1/0627/6022/2782/files/S58f0e875d1d54ef6b0152e99423ad7463_e9e793e6-5ea8-4e05-9287-56cdb21ae0a6.webp?v=1752125920",
                "altText": null
            },
            {
                "url": "https://cdn.shopify.com/s/files/1/0627/6022/2782/files/S3727d58e028145ef8431366e9a1b15dcF_ba2cf597-0aa8-42e4-aa19-0b931ed09140.webp?v=1752125920",
                "altText": null
            },
            {
                "url": "https://cdn.shopify.com/s/files/1/0627/6022/2782/files/Se189921dd1714225841d3e6a30a62065d_21a07fec-b15f-4308-959c-b258e8f40ad4.webp?v=1752125920",
                "altText": null
            },
            {
                "url": "https://cdn.shopify.com/s/files/1/0627/6022/2782/files/Sed30f46644fc4d1c923ee8e9311513f2q_5520133c-77b8-4a48-a88e-1f464b672413.webp?v=1752125920",
                "altText": null
            },
            {
                "url": "https://cdn.shopify.com/s/files/1/0627/6022/2782/files/S1efb47b43c9547f587206c860bf8d1deo_a7082105-1359-4420-9b64-ad2279b4883d.webp?v=1752125920",
                "altText": null
            },
            {
                "url": "https://cdn.shopify.com/s/files/1/0627/6022/2782/files/S240f5e5c0b28454db1b92d9e427fb893B_1c6ac7c7-a3fb-48fa-ad68-e4f46d8c6222.webp?v=1752125920",
                "altText": null
            },
            {
                "url": "https://cdn.shopify.com/s/files/1/0627/6022/2782/files/S659e01cee39b4e65a98f31c6ad4c6ad2T_52f0ed7b-5f87-40eb-b2a5-6709ea59ebe0.webp?v=1752125920",
                "altText": null
            },
            {
                "url": "https://cdn.shopify.com/s/files/1/0627/6022/2782/files/Sea5e48ada63b42b28e9f00d79bbbf69ay_7f03030b-02a3-4675-ba26-3f8f8e6a9264.webp?v=1752125921",
                "altText": null
            },
            {
                "url": "https://cdn.shopify.com/s/files/1/0627/6022/2782/files/Se18dc07ef89b459c846da75fc7eb0e00F_b3b66e39-5aae-4b2a-9798-394821193d1c.webp?v=1752125920",
                "altText": null
            },
            {
                "url": "https://cdn.shopify.com/s/files/1/0627/6022/2782/files/Sbc3e076d03f94b168845a6fc346ae75fA_b86b6f0d-d986-4452-9dab-c0985b970920.webp?v=1752125921",
                "altText": null
            }
        ],
        "variants": [
            {
                "id": "41841853857854",
                "title": "7C Orange / 100M",
                "sku": "14:173#7C Orange;200085263:200007633#100M",
                "price": 46.29,
                "compareAtPrice": 46.29,
                "inventory": 19
            },
            {
                "id": "41841853890622",
                "title": "7C Army green / 50M",
                "sku": "14:10#7C Army green;200085263:200007637#50M",
                "price": 25.42,
                "compareAtPrice": 25.42,
                "inventory": 28
            },
            {
                "id": "41841853923390",
                "title": "7C Brown / 100M",
                "sku": "14:175#7C Brown;200085263:200007633#100M",
                "price": 46.26,
                "compareAtPrice": 46.26,
                "inventory": 26
            },
            {
                "id": "41841853956158",
                "title": "7C Orange / 50M",
                "sku": "14:173#7C Orange;200085263:200007637#50M",
                "price": 24.12,
                "compareAtPrice": 24.12,
                "inventory": 11
            },
            {
                "id": "41841853988926",
                "title": "7C Black / 100M",
                "sku": "14:350853#7C Black;200085263:200007633#100M",
                "price": 46.42,
                "compareAtPrice": 46.42,
                "inventory": 67
            },
            {
                "id": "41841854021694",
                "title": "7C Army green / 100M",
                "sku": "14:10#7C Army green;200085263:200007633#100M",
                "price": 46.06,
                "compareAtPrice": 46.06,
                "inventory": 21
            },
            {
                "id": "41841854054462",
                "title": "7C Black / 50M",
                "sku": "14:350853#7C Black;200085263:200007637#50M",
                "price": 24.49,
                "compareAtPrice": 24.49,
                "inventory": 44
            },
            {
                "id": "41841854087230",
                "title": "7C Camouflage / 100M",
                "sku": "14:201618806#7C Camouflage;200085263:200007633#100M",
                "price": 45.52,
                "compareAtPrice": 45.52,
                "inventory": 22
            },
            {
                "id": "41841854119998",
                "title": "7C Red / 50M",
                "sku": "14:366#7C Red;200085263:200007637#50M",
                "price": 24.29,
                "compareAtPrice": 24.29,
                "inventory": 25
            },
            {
                "id": "41841854152766",
                "title": "7C Red Camouflage / 100M",
                "sku": "14:350686#7C Red Camouflage;200085263:200007633#100M",
                "price": 45.66,
                "compareAtPrice": 45.66,
                "inventory": 22
            },
            {
                "id": "41841854185534",
                "title": "7C Camouflage / 50M",
                "sku": "14:201618806#7C Camouflage;200085263:200007637#50M",
                "price": 23.99,
                "compareAtPrice": 23.99,
                "inventory": 16
            },
            {
                "id": "41841854218302",
                "title": "7C Blue / 100M",
                "sku": "14:193#7C Blue;200085263:200007633#100M",
                "price": 45.36,
                "compareAtPrice": 45.36,
                "inventory": 21
            },
            {
                "id": "41841854251070",
                "title": "7C Brown / 50M",
                "sku": "14:175#7C Brown;200085263:200007637#50M",
                "price": 24.39,
                "compareAtPrice": 24.39,
                "inventory": 14
            },
            {
                "id": "41841854283838",
                "title": "7C Red / 100M",
                "sku": "14:366#7C Red;200085263:200007633#100M",
                "price": 46.02,
                "compareAtPrice": 46.02,
                "inventory": 28
            },
            {
                "id": "41841854316606",
                "title": "7C Blue / 50M",
                "sku": "14:193#7C Blue;200085263:200007637#50M",
                "price": 25.12,
                "compareAtPrice": 25.12,
                "inventory": 18
            },
            {
                "id": "41841854349374",
                "title": "7C Orange Camouflage / 31M",
                "sku": "14:200572156#7C Orange Camouflage;200085263:4#31M",
                "price": 16.61,
                "compareAtPrice": 16.61,
                "inventory": 23
            },
            {
                "id": "41841854382142",
                "title": "7C Deserts / 50M",
                "sku": "14:350852#7C Deserts;200085263:200007637#50M",
                "price": 23.99,
                "compareAtPrice": 23.99,
                "inventory": 15
            },
            {
                "id": "41841854414910",
                "title": "7C Deserts / 31M",
                "sku": "14:350852#7C Deserts;200085263:4#31M",
                "price": 16.48,
                "compareAtPrice": 16.48,
                "inventory": 30
            },
            {
                "id": "41841854447678",
                "title": "7C Orange Camouflage / 100M",
                "sku": "14:200572156#7C Orange Camouflage;200085263:200007633#100M",
                "price": 46.26,
                "compareAtPrice": 46.26,
                "inventory": 13
            },
            {
                "id": "41841854480446",
                "title": "7C Red Camouflage / 50M",
                "sku": "14:350686#7C Red Camouflage;200085263:200007637#50M",
                "price": 24.12,
                "compareAtPrice": 24.12,
                "inventory": 20
            },
            {
                "id": "41841854513214",
                "title": "7C Deserts / 100M",
                "sku": "14:350852#7C Deserts;200085263:200007633#100M",
                "price": 45.72,
                "compareAtPrice": 45.72,
                "inventory": 28
            },
            {
                "id": "41841854545982",
                "title": "7C Orange Camouflage / 50M",
                "sku": "14:200572156#7C Orange Camouflage;200085263:200007637#50M",
                "price": 24.39,
                "compareAtPrice": 24.39,
                "inventory": 12
            },
            {
                "id": "41841854578750",
                "title": "7C Black / 31M",
                "sku": "14:350853#7C Black;200085263:4#31M",
                "price": 16.71,
                "compareAtPrice": 16.71,
                "inventory": 51
            },
            {
                "id": "41841854611518",
                "title": "7C Army green / 31M",
                "sku": "14:10#7C Army green;200085263:4#31M",
                "price": 15.78,
                "compareAtPrice": 15.78,
                "inventory": 37
            },
            {
                "id": "41841854644286",
                "title": "7C Orange / 31M",
                "sku": "14:173#7C Orange;200085263:4#31M",
                "price": 16.42,
                "compareAtPrice": 16.42,
                "inventory": 16
            },
            {
                "id": "41841854677054",
                "title": "7C Brown / 31M",
                "sku": "14:175#7C Brown;200085263:4#31M",
                "price": 16.25,
                "compareAtPrice": 16.25,
                "inventory": 25
            },
            {
                "id": "41841854709822",
                "title": "7C Blue / 31M",
                "sku": "14:193#7C Blue;200085263:4#31M",
                "price": 16.52,
                "compareAtPrice": 16.52,
                "inventory": 4
            },
            {
                "id": "41841854742590",
                "title": "7C Red / 31M",
                "sku": "14:366#7C Red;200085263:4#31M",
                "price": 16.52,
                "compareAtPrice": 16.52,
                "inventory": 18
            },
            {
                "id": "41841854775358",
                "title": "7C Camouflage / 31M",
                "sku": "14:201618806#7C Camouflage;200085263:4#31M",
                "price": 16.52,
                "compareAtPrice": 16.52,
                "inventory": 30
            },
            {
                "id": "41841854808126",
                "title": "7C Red Camouflage / 31M",
                "sku": "14:350686#7C Red Camouflage;200085263:4#31M",
                "price": 16.52,
                "compareAtPrice": 16.52,
                "inventory": 68
            }
        ],
        "price": 46.29,
        "currency": "ILS",
        "syncedAt": "2025-07-10T09:49:30.353587+00:00"
    },
    {
        "_id": "7818534584382",
        "id": "7818534584382",
        "title": "Portable Stainless Steel Wire Saw with Finger Handle Outdoor Camping Hiking Pocket Manual Cutting Chain Saws Survive Tool",
        "description": "<h1>SPECIFICATIONS</h1><p><span>Brand Name</span>: <span style=\"color:#333\">NoEnName_Null</span></p><p><span>Choice</span>: <span style=\"color:#333\">yes</span></p><p><span>Electric</span>: <span style=\"color:#333\">No</span></p><p><span>Hign-concerned Chemical</span>: <span style=\"color:#333\">None</span></p><p><span>Origin</span>: <span style=\"color:#333\">Mainland China</span></p><p><span>Type</span>: <span style=\"color:#333\">Camping Saws</span></p><div style='font-family:\"Open Sans\", Roboto, Arial, Helvetica, sans-serif, SimSun;font-size:14px;font-weight:400;letter-spacing:normal;text-align:start;white-space:normal;color:rgb(34, 34, 34);background-color:rgb(255, 255, 255);margin:0px;margin-bottom:0px;margin-top:0px;margin-left:0px;margin-right:0px;padding:0px;padding-bottom:0px;padding-top:0px;padding-left:0px;padding-right:0px;box-sizing:content-box' align=\"start\">\n<span style=\"font-size:16px\">Steel portable wire saw as survival tool can be sawing wood plastic bones rubber soft metal and other materials</span><br><span style=\"font-size:16px\">Steel wire with 2 plastic finger hook handle</span><br><span style=\"font-size:16px\">Good quality, saw blade sharp, small size, light weight, easy to carry</span><br><span style=\"font-size:16px\">Don't try to cut with the wire saw in a U shape. The straighter it is the better</span><br><span style=\"font-size:16px\">Type:saw</span><br><span style=\"font-size:16px\">Color:silver &amp; black</span><br><span style=\"font-size:16px\">Material:steel &amp; plastic</span><br><span style=\"font-size:16px\">Size:7cm x 4cm x 1.7cm</span><br><span style=\"font-size:16px\">Length:72cm</span><br><span style=\"font-size:16px\">Package includes:1pc saw</span>\n</div><p><br><img src=\"https://ae01.alicdn.com/kf/S7ff0cf72c1d94de5be7ced5995125ae5P.jpg\" slate-data-type=\"image\"><img src=\"https://ae01.alicdn.com/kf/Sc7a5032394ed42f7a443e753a0fb43ebi.jpg\" slate-data-type=\"image\"><img src=\"https://ae01.alicdn.com/kf/S6d524d1c8e524813b99781f705a60204X.jpg\" slate-data-type=\"image\"><img src=\"https://ae01.alicdn.com/kf/Sbd6b206d0f934e59934610f9965fe78ci.jpg\" slate-data-type=\"image\"><img src=\"https://ae01.alicdn.com/kf/S63ec879542734e22975ed471696af45cW.jpg\" slate-data-type=\"image\"><img src=\"https://ae01.alicdn.com/kf/Sae704f6d264048548ec54328f2a598029.jpg\" slate-data-type=\"image\"><img src=\"https://ae01.alicdn.com/kf/Sbd732399c92b48ba887d34c38dc5adb0H.jpg\" slate-data-type=\"image\"></p>",
        "vendor": "My Store",
        "productType": "",
        "handle": "portable-stainless-steel-wire-saw-with-finger-handle-outdoor-camping-hiking-pocket-manual-cutting-chain-saws-survive-tool",
        "status": "ACTIVE",
        "tags": [],
        "images": [
            {
                "url": "https://cdn.shopify.com/s/files/1/0627/6022/2782/files/S14ab081bb03448cd894f3ce18707b153s.webp?v=1752125916",
                "altText": null
            },
            {
                "url": "https://cdn.shopify.com/s/files/1/0627/6022/2782/files/S3b6f6f17be464f6f82e51646b1e22dfcI.webp?v=1752125915",
                "altText": null
            },
            {
                "url": "https://cdn.shopify.com/s/files/1/0627/6022/2782/files/Saec23b33248d4885ba11fe3b14506996L.webp?v=1752125915",
                "altText": null
            },
            {
                "url": "https://cdn.shopify.com/s/files/1/0627/6022/2782/files/S72c02e15fdb444b8814c0ba4ebae8655R.webp?v=1752125916",
                "altText": null
            },
            {
                "url": "https://cdn.shopify.com/s/files/1/0627/6022/2782/files/Sab55381b6e34486886a977fd9e6be3d43.webp?v=1752125916",
                "altText": null
            },
            {
                "url": "https://cdn.shopify.com/s/files/1/0627/6022/2782/files/Se30272b8879346c1a877745f7e285268g.webp?v=1752125915",
                "altText": null
            },
            {
                "url": "https://cdn.shopify.com/s/files/1/0627/6022/2782/files/S2d1855a0f5974d24b07351e626474f72n.webp?v=1752125916",
                "altText": null
            },
            {
                "url": "https://cdn.shopify.com/s/files/1/0627/6022/2782/files/S0ffafa76593c4ab38ded8854ce09acadc.webp?v=1752125916",
                "altText": null
            }
        ],
        "variants": [
            {
                "id": "41841853300798",
                "title": "black",
                "sku": "14:193#black",
                "price": 7.64,
                "compareAtPrice": 7.64,
                "inventory": 23
            },
            {
                "id": "41841853333566",
                "title": "red",
                "sku": "14:10#red",
                "price": 7.11,
                "compareAtPrice": 7.11,
                "inventory": 20
            }
        ],
        "price": 7.64,
        "currency": "ILS",
        "syncedAt": "2025-07-10T09:49:30.353587+00:00"
    }
]